{
  "id": "0aed62d5-22c6-45ac-b72a-383294f62fee",
  "prevId": "0ea06bcd-24db-43eb-a6a4-e9f0f6b89619",
  "version": "7",
  "dialect": "postgresql",
  "tables": {
    "public.competitor_attachments": {
      "name": "competitor_attachments",
      "schema": "",
      "columns": {
        "id": {
          "name": "id",
          "type": "serial",
          "primaryKey": true,
          "notNull": true
        },
        "competitor_id": {
          "name": "competitor_id",
          "type": "integer",
          "primaryKey": false,
          "notNull": true
        },
        "name": {
          "name": "name",
          "type": "text",
          "primaryKey": false,
          "notNull": true
        },
        "size": {
          "name": "size",
          "type": "bigint",
          "primaryKey": false,
          "notNull": true,
          "default": 0
        },
        "mime_type": {
          "name": "mime_type",
          "type": "text",
          "primaryKey": false,
          "notNull": false
        },
        "url": {
          "name": "url",
          "type": "text",
          "primaryKey": false,
          "notNull": true
        },
        "blob_pathname": {
          "name": "blob_pathname",
          "type": "text",
          "primaryKey": false,
          "notNull": false
        },
        "uploader_clerk_id": {
          "name": "uploader_clerk_id",
          "type": "text",
          "primaryKey": false,
          "notNull": false
        },
        "added_at": {
          "name": "added_at",
          "type": "timestamp",
          "primaryKey": false,
          "notNull": true,
          "default": "now()"
        }
      },
      "indexes": {
        "competitor_attachments_competitor_idx": {
          "name": "competitor_attachments_competitor_idx",
          "columns": [
            {
              "expression": "competitor_id",
              "isExpression": false,
              "asc": true,
              "nulls": "last"
            }
          ],
          "isUnique": false,
          "concurrently": false,
          "method": "btree",
          "with": {}
        }
      },
      "foreignKeys": {
        "competitor_attachments_competitor_id_competitors_id_fk": {
          "name": "competitor_attachments_competitor_id_competitors_id_fk",
          "tableFrom": "competitor_attachments",
          "tableTo": "competitors",
          "columnsFrom": [
            "competitor_id"
          ],
          "columnsTo": [
            "id"
          ],
          "onDelete": "cascade",
          "onUpdate": "no action"
        }
      },
      "compositePrimaryKeys": {},
      "uniqueConstraints": {},
      "policies": {},
      "checkConstraints": {},
      "isRLSEnabled": false
    },
    "public.competitor_collections": {
      "name": "competitor_collections",
      "schema": "",
      "columns": {
        "id": {
          "name": "id",
          "type": "serial",
          "primaryKey": true,
          "notNull": true
        },
        "name": {
          "name": "name",
          "type": "text",
          "primaryKey": false,
          "notNull": true
        },
        "description": {
          "name": "description",
          "type": "text",
          "primaryKey": false,
          "notNull": false
        },
        "created_by_clerk_id": {
          "name": "created_by_clerk_id",
          "type": "text",
          "primaryKey": false,
          "notNull": false
        },
        "created_at": {
          "name": "created_at",
          "type": "timestamp",
          "primaryKey": false,
          "notNull": true,
          "default": "now()"
        },
        "updated_at": {
          "name": "updated_at",
          "type": "timestamp",
          "primaryKey": false,
          "notNull": true,
          "default": "now()"
        }
      },
      "indexes": {
        "competitor_collections_name_idx": {
          "name": "competitor_collections_name_idx",
          "columns": [
            {
              "expression": "name",
              "isExpression": false,
              "asc": true,
              "nulls": "last"
            }
          ],
          "isUnique": false,
          "concurrently": false,
          "method": "btree",
          "with": {}
        }
      },
      "foreignKeys": {},
      "compositePrimaryKeys": {},
      "uniqueConstraints": {},
      "policies": {},
      "checkConstraints": {},
      "isRLSEnabled": false
    },
    "public.competitor_product_attachments": {
      "name": "competitor_product_attachments",
      "schema": "",
      "columns": {
        "id": {
          "name": "id",
          "type": "serial",
          "primaryKey": true,
          "notNull": true
        },
        "product_id": {
          "name": "product_id",
          "type": "integer",
          "primaryKey": false,
          "notNull": true
        },
        "name": {
          "name": "name",
          "type": "text",
          "primaryKey": false,
          "notNull": true
        },
        "size": {
          "name": "size",
          "type": "bigint",
          "primaryKey": false,
          "notNull": true,
          "default": 0
        },
        "mime_type": {
          "name": "mime_type",
          "type": "text",
          "primaryKey": false,
          "notNull": false
        },
        "kind": {
          "name": "kind",
          "type": "text",
          "primaryKey": false,
          "notNull": false
        },
        "url": {
          "name": "url",
          "type": "text",
          "primaryKey": false,
          "notNull": true
        },
        "blob_pathname": {
          "name": "blob_pathname",
          "type": "text",
          "primaryKey": false,
          "notNull": false
        },
        "uploader_clerk_id": {
          "name": "uploader_clerk_id",
          "type": "text",
          "primaryKey": false,
          "notNull": false
        },
        "added_at": {
          "name": "added_at",
          "type": "timestamp",
          "primaryKey": false,
          "notNull": true,
          "default": "now()"
        }
      },
      "indexes": {
        "competitor_product_attachments_product_idx": {
          "name": "competitor_product_attachments_product_idx",
          "columns": [
            {
              "expression": "product_id",
              "isExpression": false,
              "asc": true,
              "nulls": "last"
            }
          ],
          "isUnique": false,
          "concurrently": false,
          "method": "btree",
          "with": {}
        }
      },
      "foreignKeys": {
        "competitor_product_attachments_product_id_competitor_products_id_fk": {
          "name": "competitor_product_attachments_product_id_competitor_products_id_fk",
          "tableFrom": "competitor_product_attachments",
          "tableTo": "competitor_products",
          "columnsFrom": [
            "product_id"
          ],
          "columnsTo": [
            "id"
          ],
          "onDelete": "cascade",
          "onUpdate": "no action"
        }
      },
      "compositePrimaryKeys": {},
      "uniqueConstraints": {},
      "policies": {},
      "checkConstraints": {},
      "isRLSEnabled": false
    },
    "public.competitor_products": {
      "name": "competitor_products",
      "schema": "",
      "columns": {
        "id": {
          "name": "id",
          "type": "serial",
          "primaryKey": true,
          "notNull": true
        },
        "competitor_id": {
          "name": "competitor_id",
          "type": "integer",
          "primaryKey": false,
          "notNull": true
        },
        "name": {
          "name": "name",
          "type": "text",
          "primaryKey": false,
          "notNull": true
        },
        "product_code": {
          "name": "product_code",
          "type": "text",
          "primaryKey": false,
          "notNull": false
        },
        "product_category": {
          "name": "product_category",
          "type": "text",
          "primaryKey": false,
          "notNull": false
        },
        "description": {
          "name": "description",
          "type": "text",
          "primaryKey": false,
          "notNull": false
        },
        "image_urls": {
          "name": "image_urls",
          "type": "text[]",
          "primaryKey": false,
          "notNull": true,
          "default": "ARRAY[]::text[]"
        },
        "specs": {
          "name": "specs",
          "type": "jsonb",
          "primaryKey": false,
          "notNull": true,
          "default": "'{}'::jsonb"
        },
        "source_url": {
          "name": "source_url",
          "type": "text",
          "primaryKey": false,
          "notNull": false
        },
        "created_at": {
          "name": "created_at",
          "type": "timestamp",
          "primaryKey": false,
          "notNull": true,
          "default": "now()"
        },
        "updated_at": {
          "name": "updated_at",
          "type": "timestamp",
          "primaryKey": false,
          "notNull": true,
          "default": "now()"
        }
      },
      "indexes": {
        "competitor_products_competitor_idx": {
          "name": "competitor_products_competitor_idx",
          "columns": [
            {
              "expression": "competitor_id",
              "isExpression": false,
              "asc": true,
              "nulls": "last"
            }
          ],
          "isUnique": false,
          "concurrently": false,
          "method": "btree",
          "with": {}
        },
        "competitor_products_name_idx": {
          "name": "competitor_products_name_idx",
          "columns": [
            {
              "expression": "name",
              "isExpression": false,
              "asc": true,
              "nulls": "last"
            }
          ],
          "isUnique": false,
          "concurrently": false,
          "method": "btree",
          "with": {}
        }
      },
      "foreignKeys": {
        "competitor_products_competitor_id_competitors_id_fk": {
          "name": "competitor_products_competitor_id_competitors_id_fk",
          "tableFrom": "competitor_products",
          "tableTo": "competitors",
          "columnsFrom": [
            "competitor_id"
          ],
          "columnsTo": [
            "id"
          ],
          "onDelete": "cascade",
          "onUpdate": "no action"
        }
      },
      "compositePrimaryKeys": {},
      "uniqueConstraints": {},
      "policies": {},
      "checkConstraints": {},
      "isRLSEnabled": false
    },
    "public.competitors": {
      "name": "competitors",
      "schema": "",
      "columns": {
        "id": {
          "name": "id",
          "type": "serial",
          "primaryKey": true,
          "notNull": true
        },
        "collection_id": {
          "name": "collection_id",
          "type": "integer",
          "primaryKey": false,
          "notNull": true
        },
        "name": {
          "name": "name",
          "type": "text",
          "primaryKey": false,
          "notNull": true
        },
        "website": {
          "name": "website",
          "type": "text",
          "primaryKey": false,
          "notNull": false
        },
        "parent": {
          "name": "parent",
          "type": "text",
          "primaryKey": false,
          "notNull": false
        },
        "tier_key": {
          "name": "tier_key",
          "type": "competitor_tier",
          "typeSchema": "public",
          "primaryKey": false,
          "notNull": true,
          "default": "'mid'"
        },
        "tier": {
          "name": "tier",
          "type": "text",
          "primaryKey": false,
          "notNull": false
        },
        "segment": {
          "name": "segment",
          "type": "text",
          "primaryKey": false,
          "notNull": false
        },
        "country": {
          "name": "country",
          "type": "text",
          "primaryKey": false,
          "notNull": false
        },
        "product_lines": {
          "name": "product_lines",
          "type": "text",
          "primaryKey": false,
          "notNull": false
        },
        "channel": {
          "name": "channel",
          "type": "text",
          "primaryKey": false,
          "notNull": false
        },
        "notes": {
          "name": "notes",
          "type": "text",
          "primaryKey": false,
          "notNull": false
        },
        "capabilities": {
          "name": "capabilities",
          "type": "text[]",
          "primaryKey": false,
          "notNull": true,
          "default": "ARRAY[]::text[]"
        },
        "created_at": {
          "name": "created_at",
          "type": "timestamp",
          "primaryKey": false,
          "notNull": true,
          "default": "now()"
        },
        "updated_at": {
          "name": "updated_at",
          "type": "timestamp",
          "primaryKey": false,
          "notNull": true,
          "default": "now()"
        }
      },
      "indexes": {
        "competitors_collection_idx": {
          "name": "competitors_collection_idx",
          "columns": [
            {
              "expression": "collection_id",
              "isExpression": false,
              "asc": true,
              "nulls": "last"
            }
          ],
          "isUnique": false,
          "concurrently": false,
          "method": "btree",
          "with": {}
        },
        "competitors_name_idx": {
          "name": "competitors_name_idx",
          "columns": [
            {
              "expression": "name",
              "isExpression": false,
              "asc": true,
              "nulls": "last"
            }
          ],
          "isUnique": false,
          "concurrently": false,
          "method": "btree",
          "with": {}
        },
        "competitors_tier_idx": {
          "name": "competitors_tier_idx",
          "columns": [
            {
              "expression": "tier_key",
              "isExpression": false,
              "asc": true,
              "nulls": "last"
            }
          ],
          "isUnique": false,
          "concurrently": false,
          "method": "btree",
          "with": {}
        }
      },
      "foreignKeys": {
        "competitors_collection_id_competitor_collections_id_fk": {
          "name": "competitors_collection_id_competitor_collections_id_fk",
          "tableFrom": "competitors",
          "tableTo": "competitor_collections",
          "columnsFrom": [
            "collection_id"
          ],
          "columnsTo": [
            "id"
          ],
          "onDelete": "cascade",
          "onUpdate": "no action"
        }
      },
      "compositePrimaryKeys": {},
      "uniqueConstraints": {},
      "policies": {},
      "checkConstraints": {},
      "isRLSEnabled": false
    },
    "public.handbook_revisions": {
      "name": "handbook_revisions",
      "schema": "",
      "columns": {
        "id": {
          "name": "id",
          "type": "serial",
          "primaryKey": true,
          "notNull": true
        },
        "owner_clerk_id": {
          "name": "owner_clerk_id",
          "type": "text",
          "primaryKey": false,
          "notNull": true
        },
        "name": {
          "name": "name",
          "type": "text",
          "primaryKey": false,
          "notNull": true,
          "default": "'Untitled'"
        },
        "content": {
          "name": "content",
          "type": "jsonb",
          "primaryKey": false,
          "notNull": true
        },
        "status": {
          "name": "status",
          "type": "handbook_revision_status",
          "typeSchema": "public",
          "primaryKey": false,
          "notNull": true,
          "default": "'draft'"
        },
        "created_at": {
          "name": "created_at",
          "type": "timestamp",
          "primaryKey": false,
          "notNull": true,
          "default": "now()"
        },
        "updated_at": {
          "name": "updated_at",
          "type": "timestamp",
          "primaryKey": false,
          "notNull": true,
          "default": "now()"
        }
      },
      "indexes": {
        "handbook_revisions_owner_idx": {
          "name": "handbook_revisions_owner_idx",
          "columns": [
            {
              "expression": "owner_clerk_id",
              "isExpression": false,
              "asc": true,
              "nulls": "last"
            }
          ],
          "isUnique": false,
          "concurrently": false,
          "method": "btree",
          "with": {}
        },
        "handbook_revisions_status_idx": {
          "name": "handbook_revisions_status_idx",
          "columns": [
            {
              "expression": "status",
              "isExpression": false,
              "asc": true,
              "nulls": "last"
            }
          ],
          "isUnique": false,
          "concurrently": false,
          "method": "btree",
          "with": {}
        }
      },
      "foreignKeys": {},
      "compositePrimaryKeys": {},
      "uniqueConstraints": {},
      "policies": {},
      "checkConstraints": {},
      "isRLSEnabled": false
    },
    "public.supplier_attachments": {
      "name": "supplier_attachments",
      "schema": "",
      "columns": {
        "id": {
          "name": "id",
          "type": "serial",
          "primaryKey": true,
          "notNull": true
        },
        "supplier_id": {
          "name": "supplier_id",
          "type": "integer",
          "primaryKey": false,
          "notNull": true
        },
        "cat_id": {
          "name": "cat_id",
          "type": "text",
          "primaryKey": false,
          "notNull": true
        },
        "name": {
          "name": "name",
          "type": "text",
          "primaryKey": false,
          "notNull": true
        },
        "size": {
          "name": "size",
          "type": "bigint",
          "primaryKey": false,
          "notNull": true,
          "default": 0
        },
        "mime_type": {
          "name": "mime_type",
          "type": "text",
          "primaryKey": false,
          "notNull": false
        },
        "url": {
          "name": "url",
          "type": "text",
          "primaryKey": false,
          "notNull": true
        },
        "blob_pathname": {
          "name": "blob_pathname",
          "type": "text",
          "primaryKey": false,
          "notNull": false
        },
        "uploader": {
          "name": "uploader",
          "type": "text",
          "primaryKey": false,
          "notNull": false
        },
        "uploader_clerk_id": {
          "name": "uploader_clerk_id",
          "type": "text",
          "primaryKey": false,
          "notNull": false
        },
        "date": {
          "name": "date",
          "type": "date",
          "primaryKey": false,
          "notNull": true,
          "default": "now()"
        },
        "created_at": {
          "name": "created_at",
          "type": "timestamp",
          "primaryKey": false,
          "notNull": true,
          "default": "now()"
        }
      },
      "indexes": {
        "supplier_attachments_supplier_idx": {
          "name": "supplier_attachments_supplier_idx",
          "columns": [
            {
              "expression": "supplier_id",
              "isExpression": false,
              "asc": true,
              "nulls": "last"
            }
          ],
          "isUnique": false,
          "concurrently": false,
          "method": "btree",
          "with": {}
        },
        "supplier_attachments_cat_idx": {
          "name": "supplier_attachments_cat_idx",
          "columns": [
            {
              "expression": "cat_id",
              "isExpression": false,
              "asc": true,
              "nulls": "last"
            }
          ],
          "isUnique": false,
          "concurrently": false,
          "method": "btree",
          "with": {}
        }
      },
      "foreignKeys": {
        "supplier_attachments_supplier_id_suppliers_id_fk": {
          "name": "supplier_attachments_supplier_id_suppliers_id_fk",
          "tableFrom": "supplier_attachments",
          "tableTo": "suppliers",
          "columnsFrom": [
            "supplier_id"
          ],
          "columnsTo": [
            "id"
          ],
          "onDelete": "cascade",
          "onUpdate": "no action"
        }
      },
      "compositePrimaryKeys": {},
      "uniqueConstraints": {},
      "policies": {},
      "checkConstraints": {},
      "isRLSEnabled": false
    },
    "public.supplier_comments": {
      "name": "supplier_comments",
      "schema": "",
      "columns": {
        "id": {
          "name": "id",
          "type": "serial",
          "primaryKey": true,
          "notNull": true
        },
        "supplier_id": {
          "name": "supplier_id",
          "type": "integer",
          "primaryKey": false,
          "notNull": true
        },
        "text": {
          "name": "text",
          "type": "text",
          "primaryKey": false,
          "notNull": true
        },
        "project_num": {
          "name": "project_num",
          "type": "text",
          "primaryKey": false,
          "notNull": false
        },
        "author": {
          "name": "author",
          "type": "text",
          "primaryKey": false,
          "notNull": false
        },
        "author_clerk_id": {
          "name": "author_clerk_id",
          "type": "text",
          "primaryKey": false,
          "notNull": false
        },
        "date": {
          "name": "date",
          "type": "date",
          "primaryKey": false,
          "notNull": true,
          "default": "now()"
        },
        "created_at": {
          "name": "created_at",
          "type": "timestamp",
          "primaryKey": false,
          "notNull": true,
          "default": "now()"
        }
      },
      "indexes": {
        "supplier_comments_supplier_idx": {
          "name": "supplier_comments_supplier_idx",
          "columns": [
            {
              "expression": "supplier_id",
              "isExpression": false,
              "asc": true,
              "nulls": "last"
            }
          ],
          "isUnique": false,
          "concurrently": false,
          "method": "btree",
          "with": {}
        }
      },
      "foreignKeys": {
        "supplier_comments_supplier_id_suppliers_id_fk": {
          "name": "supplier_comments_supplier_id_suppliers_id_fk",
          "tableFrom": "supplier_comments",
          "tableTo": "suppliers",
          "columnsFrom": [
            "supplier_id"
          ],
          "columnsTo": [
            "id"
          ],
          "onDelete": "cascade",
          "onUpdate": "no action"
        }
      },
      "compositePrimaryKeys": {},
      "uniqueConstraints": {},
      "policies": {},
      "checkConstraints": {},
      "isRLSEnabled": false
    },
    "public.supplier_project_entries": {
      "name": "supplier_project_entries",
      "schema": "",
      "columns": {
        "id": {
          "name": "id",
          "type": "serial",
          "primaryKey": true,
          "notNull": true
        },
        "supplier_id": {
          "name": "supplier_id",
          "type": "integer",
          "primaryKey": false,
          "notNull": true
        },
        "project_num": {
          "name": "project_num",
          "type": "text",
          "primaryKey": false,
          "notNull": true
        },
        "po_number": {
          "name": "po_number",
          "type": "text",
          "primaryKey": false,
          "notNull": false
        },
        "status": {
          "name": "status",
          "type": "project_entry_status",
          "typeSchema": "public",
          "primaryKey": false,
          "notNull": true,
          "default": "'Quoted'"
        },
        "quote_date": {
          "name": "quote_date",
          "type": "date",
          "primaryKey": false,
          "notNull": false
        },
        "po_date": {
          "name": "po_date",
          "type": "date",
          "primaryKey": false,
          "notNull": false
        },
        "expected_delivery": {
          "name": "expected_delivery",
          "type": "date",
          "primaryKey": false,
          "notNull": false
        },
        "actual_delivery": {
          "name": "actual_delivery",
          "type": "date",
          "primaryKey": false,
          "notNull": false
        },
        "quoted_lead_time": {
          "name": "quoted_lead_time",
          "type": "integer",
          "primaryKey": false,
          "notNull": true,
          "default": 0
        },
        "actual_lead_time": {
          "name": "actual_lead_time",
          "type": "integer",
          "primaryKey": false,
          "notNull": true,
          "default": 0
        },
        "ordered_quantity": {
          "name": "ordered_quantity",
          "type": "integer",
          "primaryKey": false,
          "notNull": true,
          "default": 0
        },
        "delivered_quantity": {
          "name": "delivered_quantity",
          "type": "integer",
          "primaryKey": false,
          "notNull": true,
          "default": 0
        },
        "defective_quantity": {
          "name": "defective_quantity",
          "type": "integer",
          "primaryKey": false,
          "notNull": true,
          "default": 0
        },
        "returned_quantity": {
          "name": "returned_quantity",
          "type": "integer",
          "primaryKey": false,
          "notNull": true,
          "default": 0
        },
        "quoted_amount": {
          "name": "quoted_amount",
          "type": "numeric(14, 2)",
          "primaryKey": false,
          "notNull": true,
          "default": "'0'"
        },
        "actual_amount": {
          "name": "actual_amount",
          "type": "numeric(14, 2)",
          "primaryKey": false,
          "notNull": true,
          "default": "'0'"
        },
        "currency": {
          "name": "currency",
          "type": "text",
          "primaryKey": false,
          "notNull": false,
          "default": "'USD'"
        },
        "incoterms": {
          "name": "incoterms",
          "type": "text",
          "primaryKey": false,
          "notNull": false
        },
        "payment_terms": {
          "name": "payment_terms",
          "type": "text",
          "primaryKey": false,
          "notNull": false
        },
        "notes": {
          "name": "notes",
          "type": "text",
          "primaryKey": false,
          "notNull": false
        },
        "created_at": {
          "name": "created_at",
          "type": "timestamp",
          "primaryKey": false,
          "notNull": true,
          "default": "now()"
        },
        "updated_at": {
          "name": "updated_at",
          "type": "timestamp",
          "primaryKey": false,
          "notNull": true,
          "default": "now()"
        }
      },
      "indexes": {
        "project_entries_supplier_idx": {
          "name": "project_entries_supplier_idx",
          "columns": [
            {
              "expression": "supplier_id",
              "isExpression": false,
              "asc": true,
              "nulls": "last"
            }
          ],
          "isUnique": false,
          "concurrently": false,
          "method": "btree",
          "with": {}
        },
        "project_entries_status_idx": {
          "name": "project_entries_status_idx",
          "columns": [
            {
              "expression": "status",
              "isExpression": false,
              "asc": true,
              "nulls": "last"
            }
          ],
          "isUnique": false,
          "concurrently": false,
          "method": "btree",
          "with": {}
        }
      },
      "foreignKeys": {
        "supplier_project_entries_supplier_id_suppliers_id_fk": {
          "name": "supplier_project_entries_supplier_id_suppliers_id_fk",
          "tableFrom": "supplier_project_entries",
          "tableTo": "suppliers",
          "columnsFrom": [
            "supplier_id"
          ],
          "columnsTo": [
            "id"
          ],
          "onDelete": "cascade",
          "onUpdate": "no action"
        }
      },
      "compositePrimaryKeys": {},
      "uniqueConstraints": {},
      "policies": {},
      "checkConstraints": {},
      "isRLSEnabled": false
    },
    "public.suppliers": {
      "name": "suppliers",
      "schema": "",
      "columns": {
        "id": {
          "name": "id",
          "type": "serial",
          "primaryKey": true,
          "notNull": true
        },
        "name": {
          "name": "name",
          "type": "text",
          "primaryKey": false,
          "notNull": true
        },
        "category": {
          "name": "category",
          "type": "text",
          "primaryKey": false,
          "notNull": false
        },
        "sub_category": {
          "name": "sub_category",
          "type": "text",
          "primaryKey": false,
          "notNull": false
        },
        "origin": {
          "name": "origin",
          "type": "text",
          "primaryKey": false,
          "notNull": false
        },
        "status": {
          "name": "status",
          "type": "supplier_status",
          "typeSchema": "public",
          "primaryKey": false,
          "notNull": true,
          "default": "'Active'"
        },
        "website": {
          "name": "website",
          "type": "text",
          "primaryKey": false,
          "notNull": false
        },
        "email": {
          "name": "email",
          "type": "text",
          "primaryKey": false,
          "notNull": false
        },
        "phone": {
          "name": "phone",
          "type": "text",
          "primaryKey": false,
          "notNull": false
        },
        "contact_name": {
          "name": "contact_name",
          "type": "text",
          "primaryKey": false,
          "notNull": false
        },
        "products": {
          "name": "products",
          "type": "text",
          "primaryKey": false,
          "notNull": false
        },
        "source": {
          "name": "source",
          "type": "text",
          "primaryKey": false,
          "notNull": false
        },
        "tested": {
          "name": "tested",
          "type": "text",
          "primaryKey": false,
          "notNull": false
        },
        "onboarded": {
          "name": "onboarded",
          "type": "date",
          "primaryKey": false,
          "notNull": false
        },
        "notes": {
          "name": "notes",
          "type": "text",
          "primaryKey": false,
          "notNull": false
        },
        "kpis": {
          "name": "kpis",
          "type": "jsonb",
          "primaryKey": false,
          "notNull": true,
          "default": "'{}'::jsonb"
        },
        "manufacturing_types": {
          "name": "manufacturing_types",
          "type": "text[]",
          "primaryKey": false,
          "notNull": true,
          "default": "ARRAY[]::text[]"
        },
        "materials": {
          "name": "materials",
          "type": "text[]",
          "primaryKey": false,
          "notNull": true,
          "default": "ARRAY[]::text[]"
        },
        "created_at": {
          "name": "created_at",
          "type": "timestamp",
          "primaryKey": false,
          "notNull": true,
          "default": "now()"
        },
        "updated_at": {
          "name": "updated_at",
          "type": "timestamp",
          "primaryKey": false,
          "notNull": true,
          "default": "now()"
        }
      },
      "indexes": {
        "suppliers_name_idx": {
          "name": "suppliers_name_idx",
          "columns": [
            {
              "expression": "name",
              "isExpression": false,
              "asc": true,
              "nulls": "last"
            }
          ],
          "isUnique": false,
          "concurrently": false,
          "method": "btree",
          "with": {}
        },
        "suppliers_category_idx": {
          "name": "suppliers_category_idx",
          "columns": [
            {
              "expression": "category",
              "isExpression": false,
              "asc": true,
              "nulls": "last"
            }
          ],
          "isUnique": false,
          "concurrently": false,
          "method": "btree",
          "with": {}
        },
        "suppliers_origin_idx": {
          "name": "suppliers_origin_idx",
          "columns": [
            {
              "expression": "origin",
              "isExpression": false,
              "asc": true,
              "nulls": "last"
            }
          ],
          "isUnique": false,
          "concurrently": false,
          "method": "btree",
          "with": {}
        }
      },
      "foreignKeys": {},
      "compositePrimaryKeys": {},
      "uniqueConstraints": {},
      "policies": {},
      "checkConstraints": {},
      "isRLSEnabled": false
    },
    "public.user_profiles": {
      "name": "user_profiles",
      "schema": "",
      "columns": {
        "clerk_user_id": {
          "name": "clerk_user_id",
          "type": "text",
          "primaryKey": true,
          "notNull": true
        },
        "email": {
          "name": "email",
          "type": "text",
          "primaryKey": false,
          "notNull": true
        },
        "display_name": {
          "name": "display_name",
          "type": "text",
          "primaryKey": false,
          "notNull": false
        },
        "role": {
          "name": "role",
          "type": "user_role",
          "typeSchema": "public",
          "primaryKey": false,
          "notNull": true,
          "default": "'pending'"
        },
        "can_view_suppliers": {
          "name": "can_view_suppliers",
          "type": "boolean",
          "primaryKey": false,
          "notNull": true,
          "default": false
        },
        "can_view_competitors": {
          "name": "can_view_competitors",
          "type": "boolean",
          "primaryKey": false,
          "notNull": true,
          "default": false
        },
        "can_view_handbook": {
          "name": "can_view_handbook",
          "type": "boolean",
          "primaryKey": false,
          "notNull": true,
          "default": false
        },
        "can_view_engineering": {
          "name": "can_view_engineering",
          "type": "boolean",
          "primaryKey": false,
          "notNull": true,
          "default": false
        },
        "can_edit": {
          "name": "can_edit",
          "type": "boolean",
          "primaryKey": false,
          "notNull": true,
          "default": false
        },
        "notes": {
          "name": "notes",
          "type": "text",
          "primaryKey": false,
          "notNull": false
        },
        "created_at": {
          "name": "created_at",
          "type": "timestamp",
          "primaryKey": false,
          "notNull": true,
          "default": "now()"
        },
        "updated_at": {
          "name": "updated_at",
          "type": "timestamp",
          "primaryKey": false,
          "notNull": true,
          "default": "now()"
        },
        "approved_at": {
          "name": "approved_at",
          "type": "timestamp",
          "primaryKey": false,
          "notNull": false
        },
        "approved_by": {
          "name": "approved_by",
          "type": "text",
          "primaryKey": false,
          "notNull": false
        }
      },
      "indexes": {
        "user_profiles_email_idx": {
          "name": "user_profiles_email_idx",
          "columns": [
            {
              "expression": "email",
              "isExpression": false,
              "asc": true,
              "nulls": "last"
            }
          ],
          "isUnique": true,
          "concurrently": false,
          "method": "btree",
          "with": {}
        },
        "user_profiles_role_idx": {
          "name": "user_profiles_role_idx",
          "columns": [
            {
              "expression": "role",
              "isExpression": false,
              "asc": true,
              "nulls": "last"
            }
          ],
          "isUnique": false,
          "concurrently": false,
          "method": "btree",
          "with": {}
        }
      },
      "foreignKeys": {},
      "compositePrimaryKeys": {},
      "uniqueConstraints": {},
      "policies": {},
      "checkConstraints": {},
      "isRLSEnabled": false
    }
  },
  "enums": {
    "public.competitor_tier": {
      "name": "competitor_tier",
      "schema": "public",
      "values": [
        "mass",
        "mid",
        "spec",
        "premium"
      ]
    },
    "public.handbook_revision_status": {
      "name": "handbook_revision_status",
      "schema": "public",
      "values": [
        "draft",
        "final"
      ]
    },
    "public.project_entry_status": {
      "name": "project_entry_status",
      "schema": "public",
      "values": [
        "Quoted",
        "PO Issued",
        "In Production",
        "Shipped",
        "Delivered",
        "Closed",
        "Cancelled"
      ]
    },
    "public.supplier_status": {
      "name": "supplier_status",
      "schema": "public",
      "values": [
        "Active",
        "Historical"
      ]
    },
    "public.user_role": {
      "name": "user_role",
      "schema": "public",
      "values": [
        "admin",
        "member",
        "pending"
      ]
    }
  },
  "schemas": {},
  "sequences": {},
  "roles": {},
  "policies": {},
  "views": {},
  "_meta": {
    "columns": {},
    "schemas": {},
    "tables": {}
  }
}